simplejwt_multisessions/__init__.py
simplejwt_multisessions/admin.py
simplejwt_multisessions/apps.py
simplejwt_multisessions/models.py
simplejwt_multisessions/tests.py
simplejwt_multisessions/api/serializers.py
simplejwt_multisessions/api/views.py
simplejwt_multisessions-1.4.dist-info/LICENSE
simplejwt_multisessions-1.4.dist-info/METADATA
simplejwt_multisessions-1.4.dist-info/WHEEL
simplejwt_multisessions-1.4.dist-info/top_level.txt
simplejwt_multisessions-1.4.dist-info/RECORD
