Metadata-Version: 2.1
Name: simplejwt-multisessions
Version: 1.4
Summary: A Django app that allows you to generate SIMPLE_JWT with two different lifetimes plus more options.
Home-page: https://github.com/benyaamin/simplejwt_multisessions
Author: Benyamin Agha Ebrahimi
Author-email: Benyamin.eb@gmail.com
License: MIT
Classifier: Environment :: Web Environment
Classifier: Framework :: Django
Classifier: Framework :: Django :: 3.2
Classifier: Framework :: Django :: 4.0
Classifier: Intended Audience :: Developers
Classifier: License :: OSI Approved :: MIT License
Classifier: Operating System :: OS Independent
Classifier: Programming Language :: Python
Classifier: Programming Language :: Python :: 3.8
Classifier: Programming Language :: Python :: 3.9
Classifier: Programming Language :: Python :: 3.10
Classifier: Topic :: Internet :: WWW/HTTP
Classifier: Topic :: Internet :: WWW/HTTP :: Dynamic Content
Requires-Python: >=3.8.5
License-File: LICENSE
Requires-Dist: Django (>=3.2)
Requires-Dist: djangorestframework-simplejwt (>=5.0)
